{
    "currentPlatform": "PREPAGO",
    "data": {
        "linha": "91992727418",
        "nomeCompleto": "RAIMUNDA DE LIMA CORDOVIL",
        "cpf": "35307374291",
        "telefoneContato": "",
        "dataNascimento": "03/06/1943",
        "nomeMae": null,
        "email": "nq5xuf7ppjvdgd0@gmail.com",
        "cep": "68750000",
        "endereco": "Rua POVOADO ARAPIRANGA",
        "numeroEndereco": "S/N",
        "complementoEndereco": "",
        "bairro": "SEDE",
        "cidade": "CURUCA",
        "estado": "PA",
        "logradouro": "POVOADO ARAPIRANGA",
        "contaDigital": true,
        "vencimentoFatura": null,
        "ciclo": null,
        "numeroEscolhido": "",
        "skuPlano": "VIVOCTRLF49N",
        "fluxo": "exchange"
    },
    "selectedPlatform": "CONTROLE",
    "success": "Enviamos um novo c\u00f3digo de seguran\u00e7a via SMS para o seu n\u00famero 91992727418.",
    "currentPlan": {
        "code": "TCOPREDIARIOGSM",
        "price": 0.0,
        "marketingDescription": null,
        "name": "Plano Pre Diario",
        "platform": "PREPAGO",
        "partnerBrandData": null,
        "loyalty": false
    }
}