{
    "currentPlatform": "PREPAGO",
    "data": {
        "linha": "92992703426",
        "nomeCompleto": "JANDERLANE PEREIRA MAIA",
        "cpf": "82300534215",
        "telefoneContato": "",
        "dataNascimento": "15/06/1986",
        "nomeMae": null,
        "email": null,
        "cep": "69018577",
        "endereco": "RUA AGATA ROSA",
        "numeroEndereco": "403",
        "complementoEndereco": "",
        "bairro": "LG AZUL",
        "cidade": "MANAUS",
        "estado": "AM",
        "logradouro": "AGATA ROSA",
        "contaDigital": true,
        "vencimentoFatura": null,
        "ciclo": null,
        "numeroEscolhido": "",
        "skuPlano": "VIVOCTRLF49N",
        "fluxo": "exchange"
    },
    "selectedPlatform": "CONTROLE",
    "success": "Enviamos um novo c\u00f3digo de seguran\u00e7a via SMS para o seu n\u00famero 92992703426.",
    "currentPlan": {
        "code": "TCOPREDIARIOGSM",
        "price": 0.0,
        "marketingDescription": null,
        "name": "Plano Pre Diario",
        "platform": "PREPAGO",
        "partnerBrandData": null,
        "loyalty": false
    }
}