{
    "currentPlatform": "PREPAGO",
    "link67Redirect": "https://lojaonline.vivo.com.br/checkout-express?uuid=7ae57e80-21e9-4bc8-aaf4-ab23d2fc44b9",
    "data": {
        "linha": "98991798705",
        "nomeCompleto": "SONIA MARIA FERREIRA",
        "cpf": "03213134376",
        "telefoneContato": "",
        "dataNascimento": "09/07/1981",
        "nomeMae": null,
        "email": null,
        "cep": "00000000",
        "endereco": " A",
        "numeroEndereco": "002",
        "complementoEndereco": "",
        "bairro": "MARCOS FREIRE II",
        "cidade": "NOSSA SENHORA DO SOCORRO",
        "estado": "SE",
        "logradouro": "A",
        "contaDigital": true,
        "vencimentoFatura": null,
        "ciclo": null,
        "numeroEscolhido": "",
        "skuPlano": "VIVOCTRLF49N",
        "fluxo": "exchange"
    },
    "selectedPlatform": "CONTROLE",
    "success": "Enviamos um novo c\u00f3digo de seguran\u00e7a via SMS para o seu n\u00famero 98991798705.",
    "currentPlan": {
        "code": "TCOPREDIARIOGSM",
        "price": 0.0,
        "marketingDescription": null,
        "name": "Plano Pre Diario",
        "platform": "PREPAGO",
        "partnerBrandData": null,
        "loyalty": false
    }
}